alm2/LogL-global-v5.py
alm2/__init__.py
alm2/executor.py
alm2/scrambler.py
alm2/the_data/IoT.csv
alm2/the_data/TCP.csv
alm2/the_data/TIP.csv
alm2/the_data/all_fix_counts.csv
alm2/the_data/auto.csv
alm2/the_data/bernreal-100.txt
alm2/the_data/bernreal-norm-100-digamma.txt
alm2/the_data/bernreal-norm-100.txt
alm2/the_data/cane.csv
alm2/the_data/cavallo.csv
alm2/the_data/err_coeff-100.txt
alm2/the_data/err_coeff-100_digamma.txt
alm2/the_data/err_coeff-100_trigamma.txt
alm2/the_data/f_vs_m.csv
alm2/the_data/mideast.csv
alm2/the_data/space.csv
alm2/the_data/test_fix_counts.csv
alm2/the_lib/LM_hor_shift.h
alm2/the_lib/LM_time_lib.c
alm2/the_lib/LM_time_lib.so
alm2/the_lib/constants_hor_shift.h
alm2/the_lib/init_hor_shift.h
alm2/the_lib/makefile
alm2-1.2.0.dist-info/METADATA
alm2-1.2.0.dist-info/WHEEL
alm2-1.2.0.dist-info/RECORD
