Metadata-Version: 2.1
Name: alm2
Version: 1.2.0
Summary: Python C-wrapped implementation of the LM technqiue for computing the log-likelihood function of the Dirichlet Mutlinomial Distribution with comparision to Python math and scipy implementations of the same function
Author: Alessandro Languasco (alessandro.languasco AT unipd.it), Sherenaz Al-Haj Baddar(s.baddar AT ju.edu.jo),Mauro Migliardi (mauro.migliardi AT unipd.it)
Author-email: s.baddar@ju.edu.jo
Requires-Python: >=3.11
Classifier: Programming Language :: Python :: 3
Classifier: Programming Language :: Python :: 3.11
Classifier: Programming Language :: Python :: 3.12
Requires-Dist: mpmath (>=1.3.0)
Requires-Dist: numpy (>=2.0.0)
Requires-Dist: scipy (>=1.14.0)
